nixl/__init__.py
nixl-0.9.0.dist-info/licenses/LICENSE
nixl-0.9.0.dist-info/METADATA
nixl-0.9.0.dist-info/WHEEL
nixl-0.9.0.dist-info/top_level.txt
nixl-0.9.0.dist-info/RECORD
