Metadata-Version: 2.4
Name: nixl
Version: 0.9.0
Summary: NIXL Python API meta package for CUDA variants
Author-email: NIXL Developers <nixl-developers@nvidia.com>
License-Expression: MIT AND Apache-2.0
Requires-Python: >=3.10
License-File: LICENSE
Requires-Dist: nixl-cu12>=0.9.0
Provides-Extra: cu12
Requires-Dist: nixl-cu12>=0.9.0; extra == "cu12"
Provides-Extra: cu13
Requires-Dist: nixl-cu13>=0.9.0; extra == "cu13"
Dynamic: license-file
